LICENSE
MANIFEST.in
README.rst
setup.py
potpie/__init__.py
potpie/__main__.py
potpie/core.py
potpie.egg-info/PKG-INFO
potpie.egg-info/SOURCES.txt
potpie.egg-info/dependency_links.txt
potpie.egg-info/entry_points.txt
potpie.egg-info/not-zip-safe
potpie.egg-info/requires.txt
potpie.egg-info/top_level.txt
potpie/pseudo/__init__.py
potpie/pseudo/splitters.py
potpie/pseudo/types.py