Metadata-Version: 1.0
Name: potpie
Version: 0.1.1
Summary: Translation Utility to Create Pseudo Translations of PO Files
Home-page: https://github.com/dstufft/potpie
Author: Donald Stufft
Author-email: donald.stufft@gmail.com
License:             GNU GENERAL PUBLIC LICENSE
